MANIFEST.in
README.md
requirements.txt
setup.py
test-requirements.txt
pyramid_oas3/__init__.py
pyramid_oas3/resolve.py
pyramid_oas3/tween.py
pyramid_oas3/types.py
pyramid_oas3.egg-info/PKG-INFO
pyramid_oas3.egg-info/SOURCES.txt
pyramid_oas3.egg-info/dependency_links.txt
pyramid_oas3.egg-info/requires.txt
pyramid_oas3.egg-info/top_level.txt
pyramid_oas3/jsonschema/__init__.py
pyramid_oas3/jsonschema/_formats.py
pyramid_oas3/jsonschema/_resolvers.py
pyramid_oas3/jsonschema/_utils.py
pyramid_oas3/jsonschema/_validators.py
pyramid_oas3/jsonschema/exceptions.py
pyramid_oas3/jsonschema/formats.py
pyramid_oas3/jsonschema/validators.py