Metadata-Version: 1.1
Name: pyramid-oas3
Version: 0.1.3
Summary: OpenAPI 3.0 Validator for Pyramid
Home-page: http://github.com/kazuki/pyramid-oas3
Author: Kazuki Oikawa
Author-email: k@oikw.org
License: MIT
Platform: UNKNOWN
Classifier: Programming Language :: Python :: 3
Classifier: Programming Language :: Python :: 3.5
Classifier: Programming Language :: Python :: 3.6
Classifier: Programming Language :: Python :: 3.7
Classifier: License :: OSI Approved :: MIT License
Classifier: Topic :: Software Development :: Libraries :: Python Modules
